{
  "type": "minecraft:crafting_shapeless",
  "ingredients": [
    {
      "item": "minecraft:torch"
    },
    {
      "item": "minecraft:torch"
    },
    {
      "item": "minecraft:torch"
    },
    {
      "item": "minecraft:torch"
    },
    {
      "item": "minecraft:water_bucket"
    },
    {
      "item": "minecraft:torch"
    },
    {
      "item": "minecraft:torch"
    },
    {
      "item": "minecraft:torch"
    },
    {
      "item": "minecraft:torch"
    }
  ],
  "result": {
    "item": "anomaly_rephased:unlit_torch",
    "count": 8
  }
}