{
  "pools": [
    {
      "rolls": { "min": 6, "max": 9 },
      "entries": [
        {
          "type": "minecraft:loot_table",
          "name": "tdp.509:end_crate_end",
          "weight": 6
        },
        {
          "type": "minecraft:loot_table",
          "name": "tdp.509:crate_food",
          "weight": 2
        },
        {
          "type": "minecraft:loot_table",
          "name": "tdp.509:crate_treasure",
          "weight": 4
        },
        {
          "type": "minecraft:loot_table",
          "name": "tdp.509:crate_minerals",
          "weight": 3
        }
      ]
    }
  ]
}
